Topsis_Mehak_102303724/__init__.py
Topsis_Mehak_102303724/topsis.py
topsis_mehak_102303724-1.0.2.dist-info/METADATA
topsis_mehak_102303724-1.0.2.dist-info/WHEEL
topsis_mehak_102303724-1.0.2.dist-info/entry_points.txt
topsis_mehak_102303724-1.0.2.dist-info/top_level.txt
topsis_mehak_102303724-1.0.2.dist-info/RECORD
