Metadata-Version: 2.4
Name: Topsis-Mehak-102303724
Version: 1.0.2
Summary: A package for TOPSIS implementation
Author: Mehak Goyal
Author-email: mgoyal2_be23@thapar.edu
Classifier: Programming Language :: Python :: 3
Classifier: License :: OSI Approved :: MIT License
Classifier: Operating System :: OS Independent
Requires-Python: >=3.6
Dynamic: author
Dynamic: author-email
Dynamic: classifier
Dynamic: description
Dynamic: description-content-type
Dynamic: requires-python
Dynamic: summary
